opentelemetry/semconv/ai/__init__.py
opentelemetry/semconv/ai/version.py
opentelemetry_semantic_conventions_ai_v2-0.0.7.dist-info/METADATA
opentelemetry_semantic_conventions_ai_v2-0.0.7.dist-info/WHEEL
opentelemetry_semantic_conventions_ai_v2-0.0.7.dist-info/RECORD
